less_than_key.py
less_than_key-0.1.0a0.dist-info/licenses/LICENSE
less_than_key-0.1.0a0.dist-info/METADATA
less_than_key-0.1.0a0.dist-info/WHEEL
less_than_key-0.1.0a0.dist-info/top_level.txt
less_than_key-0.1.0a0.dist-info/RECORD
