Metadata-Version: 2.4
Name: less-than-key
Version: 0.1.0a0
Summary: Custom ordering for sorting and data structures, using your own less-than (`<`) function.
Author-email: Jifeng Wu <jifengwu2k@gmail.com>
License-Expression: MIT
Project-URL: Homepage, https://github.com/jifengwu2k/less-than-key
Project-URL: Bug Tracker, https://github.com/jifengwu2k/less-than-key/issues
Classifier: Programming Language :: Python :: 2
Classifier: Programming Language :: Python :: 3
Classifier: Operating System :: OS Independent
Requires-Python: >=2
License-File: LICENSE
Requires-Dist: rawattr
Requires-Dist: six
Dynamic: license-file
